castbot/__init__.py
castbot/__main__.py
castbot/bot.py
castbot/button.py
castbot/client.py
castbot/device.py
castbot/devices/__init__.py
castbot/devices/chromecast.py
castbot/devices/upnp.py
castbot/devices/vlc.py
castbot/devices/web.py
castbot/devices/xbmc.py
castbot/downloader.py
castbot/http.py
castbot/static/index.html
castbot/utils.py
castbot/video.py
castbot-1.5.0.dist-info/LICENSE
castbot-1.5.0.dist-info/METADATA
castbot-1.5.0.dist-info/WHEEL
castbot-1.5.0.dist-info/entry_points.txt
castbot-1.5.0.dist-info/RECORD
