Metadata-Version: 2.1
Name: castbot
Version: 1.5.0
Summary: A Telegram Bot to stream contents (Telegram videos, Youtube videos and more) to your smart TV
Author: Zhongke Chen
Author-email: github@ch3n2k.com
Requires-Python: >=3.8.1,<4.0
Classifier: Programming Language :: Python :: 3
Classifier: Programming Language :: Python :: 3.9
Classifier: Programming Language :: Python :: 3.10
Classifier: Programming Language :: Python :: 3.11
Classifier: Programming Language :: Python :: 3.12
Requires-Dist: aiohttp (>=3.9,<4.0)
Requires-Dist: async-lru (>=2.0,<3.0)
Requires-Dist: async-timeout (>=4.0,<5.0)
Requires-Dist: async-upnp-client (>=0.38,<0.39)
Requires-Dist: catt (>=0.12,<0.13)
Requires-Dist: pyrogram (>=2.0,<3.0)
Requires-Dist: tgcrypto (>=1.2,<2.0)
Requires-Dist: toml (>=0.10,<0.11) ; python_version < "3.11"
Requires-Dist: you-get (>=0.4,<0.5)
Requires-Dist: yt-dlp (>=2023.11.16,<2024.0.0)
